cbc_binary_toolkit/__init__.py
cbc_binary_toolkit/cli_input.py
cbc_binary_toolkit/deduplication_component.py
cbc_binary_toolkit/engine_results.py
cbc_binary_toolkit/errors.py
cbc_binary_toolkit/ingestion_component.py
cbc_binary_toolkit/loader.py
cbc_binary_toolkit/schemas.py
cbc_binary_toolkit/ubs.py
cbc_binary_toolkit/config/__init__.py
cbc_binary_toolkit/config/errors.py
cbc_binary_toolkit/config/model.py
cbc_binary_toolkit/engine/__init__.py
cbc_binary_toolkit/engine/manager.py
cbc_binary_toolkit/state/__init__.py
cbc_binary_toolkit/state/builtin.py
cbc_binary_toolkit/state/manager.py
cbc_binary_toolkit-1.1.1.data/data/carbonblackcloud/binary-toolkit/binary-analysis-config.yaml.example
cbc_binary_toolkit_examples/__init__.py
cbc_binary_toolkit_examples/engine/__init__.py
cbc_binary_toolkit_examples/engine/yara_local/__init__.py
cbc_binary_toolkit_examples/engine/yara_local/example_rule.yara
cbc_binary_toolkit_examples/engine/yara_local/yara_engine.py
cbc_binary_toolkit_examples/tools/__init__.py
cbc_binary_toolkit_examples/tools/analysis_util.py
cbc_binary_toolkit-1.1.1.dist-info/LICENSE
cbc_binary_toolkit-1.1.1.dist-info/METADATA
cbc_binary_toolkit-1.1.1.dist-info/WHEEL
cbc_binary_toolkit-1.1.1.dist-info/entry_points.txt
cbc_binary_toolkit-1.1.1.dist-info/top_level.txt
cbc_binary_toolkit-1.1.1.dist-info/RECORD
