Metadata-Version: 2.1
Name: cbc-binary-toolkit
Version: 1.1.1
Summary: The VMware Carbon Black Cloud Binary Toolkit provides useful tools to process binaries and upload IOCs to your Feeds
Home-page: https://developer.carbonblack.com/
Author: VMware Carbon Black
Author-email: dev-support@carbonblack.com
License: MIT
Platform: any
Classifier: Development Status :: 5 - Production/Stable
Classifier: Intended Audience :: Developers
Classifier: Intended Audience :: System Administrators
Classifier: Operating System :: OS Independent
Classifier: Programming Language :: Python :: 3.6
Classifier: Programming Language :: Python :: 3.7
Classifier: Programming Language :: Python :: 3.8
Classifier: Topic :: Security
Classifier: Topic :: Software Development :: Libraries :: Python Modules
Requires-Dist: carbon-black-cloud-sdk
Requires-Dist: python-dateutil
Requires-Dist: pyyaml
Requires-Dist: requests
Requires-Dist: schema
Requires-Dist: yara-python
